{
    "version": "0.20.744",
    "description": "API Support for your favorite torrent trackers",
    "homepage": "https://github.com/Jackett/Jackett",
    "license": "GPL-2.0-or-later",
    "url": "https://github.com/Jackett/Jackett/releases/download/v0.20.744/Jackett.Binaries.Windows.zip",
    "hash": "86274fa7bea8ff583127b9d1a0e587657ae836f7f5170877f66a46aec7f2b62a",
    "shortcuts": [
        [
            "Jackett\\JackettTray.exe",
            "Jackett"
        ]
    ],
    "checkver": "github",
    "autoupdate": {
        "url": "https://github.com/Jackett/Jackett/releases/download/v$version/Jackett.Binaries.Windows.zip"
    }
}
